dask_remote/__init__.py
dask_remote/client/__init__.py
dask_remote/client/api_client.py
dask_remote/client/api_cluster.py
dask_remote/client_base.py
dask_remote/cluster_base.py
dask_remote/deployment/__init__.py
dask_remote/deployment/adaptive.py
dask_remote/deployment/deployment.py
dask_remote/deployment/k8s.py
dask_remote/runner/__init__.py
dask_remote/runner/api.py
dask_remote/runner/cli.py
dask_remote/runner/cluster_process.py
dask_remote-0.0.1a2.dist-info/LICENSE.txt
dask_remote-0.0.1a2.dist-info/WHEEL
dask_remote-0.0.1a2.dist-info/METADATA
dask_remote-0.0.1a2.dist-info/RECORD
